{"location":{"lat":-26.0908,"lng":28.0567,"name":"Inanda","country":"ZA"},"current":{"temperature":5.4,"feels_like":5.4,"humidity":92,"pressure":1031,"precipitation":0,"wind_speed":1.62,"wind_direction":108,"visibility":10,"weather_condition":"Clear","weather_description":"clear sky","cloudiness":4,"uv_index":0},"forecast":[{"datetime":"2025-08-02 06:00:00","temperature":5.58,"precipitation":0,"wind_speed":7.128,"weather_condition":"Clouds","risk_score":0},{"datetime":"2025-08-02 09:00:00","temperature":7.93,"precipitation":0,"wind_speed":10.548,"weather_condition":"Clouds","risk_score":0},{"datetime":"2025-08-02 12:00:00","temperature":12.43,"precipitation":0,"wind_speed":9.648000000000001,"weather_condition":"Clouds","risk_score":0},{"datetime":"2025-08-02 15:00:00","temperature":15.61,"precipitation":0,"wind_speed":10.656,"weather_condition":"Clear","risk_score":0},{"datetime":"2025-08-02 18:00:00","temperature":12.39,"precipitation":0,"wind_speed":8.712,"weather_condition":"Clear","risk_score":0},{"datetime":"2025-08-02 21:00:00","temperature":11.15,"precipitation":0,"wind_speed":7.884,"weather_condition":"Clear","risk_score":0},{"datetime":"2025-08-03 00:00:00","temperature":9.18,"precipitation":0,"wind_speed":7.776000000000001,"weather_condition":"Clear","risk_score":0},{"datetime":"2025-08-03 03:00:00","temperature":8.24,"precipitation":0,"wind_speed":7.416,"weather_condition":"Clear","risk_score":0}],"alerts":[],"timestamp":"2025-08-02T05:20:38.398Z"}